{
  "resource": "User",
  "resource_explanation": null,
  "http_method": "GET",
  "route": "/api/users/:id",
  "description": "show:success",
  "explanation": null,
  "parameters": [

  ],
  "response_fields": [

  ],
  "requests": [
    {
      "request_method": "GET",
      "request_path": "/api/users/136",
      "request_body": null,
      "request_headers": {
        "Content-Type": "application/json",
        "Accept": "application/json"
      },
      "request_query_parameters": {
        "{}": null
      },
      "request_content_type": "application/json",
      "response_status": 200,
      "response_status_text": "OK",
      "response_body": "{\n  \"data\": {\n    \"id\": \"136\",\n    \"type\": \"user\",\n    \"attributes\": {\n      \"id\": 136,\n      \"avatar\": \"https://robohash.org/joaquin-deflores.png?size=300x300&set=set1\",\n      \"first_name\": \"Joaquin\",\n      \"verified\": false,\n      \"fuzzy_latitude\": \"40.7292668323408\",\n      \"fuzzy_longitude\": \"-73.9330536647962\",\n      \"locality\": \"Lake Marcland\",\n      \"sublocality\": \"Willow Square\",\n      \"neighborhood\": \"Jorge Fork\",\n      \"admin_area_level_1\": \"Oklahoma\",\n      \"admin_area_level_2\": \"Yen Flat\",\n      \"images\": [\n        \"https://lorempixel.com/300/300\",\n        \"https://lorempixel.com/300/300\"\n      ],\n      \"languages\": [\n        \"en\",\n        \"fr\",\n        \"de\"\n      ],\n      \"job_position\": \"Manufacturing Manager\",\n      \"employer\": \"Herzog, Schroeder and Daniel\",\n      \"highest_education\": \"Bachelor's degree\",\n      \"school\": \"Bluemeadow University\",\n      \"facebook_uid\": \"5210467\",\n      \"instagram_user\": \"jeff.schumm\",\n      \"twitter_user\": \"jean.langosh\",\n      \"linkedin_user\": \"sung\",\n      \"created_at\": \"2019-02-18T13:52:18.249Z\",\n      \"child_ages\": [\n        2,\n        2\n      ]\n    },\n    \"relationships\": {\n      \"children\": {\n        \"data\": [\n          {\n            \"id\": \"185\",\n            \"type\": \"child\"\n          },\n          {\n            \"id\": \"186\",\n            \"type\": \"child\"\n          }\n        ]\n      }\n    }\n  },\n  \"included\": [\n    {\n      \"id\": \"185\",\n      \"type\": \"child\",\n      \"attributes\": {\n        \"parent_id\": 136,\n        \"age\": 2\n      },\n      \"relationships\": {\n        \"parent\": {\n          \"data\": {\n            \"id\": \"136\",\n            \"type\": \"user\"\n          }\n        }\n      }\n    },\n    {\n      \"id\": \"186\",\n      \"type\": \"child\",\n      \"attributes\": {\n        \"parent_id\": 136,\n        \"age\": 2\n      },\n      \"relationships\": {\n        \"parent\": {\n          \"data\": {\n            \"id\": \"136\",\n            \"type\": \"user\"\n          }\n        }\n      }\n    }\n  ]\n}",
      "response_headers": {
        "Content-Type": "application/vnd.api+json; charset=utf-8"
      },
      "response_content_type": "application/vnd.api+json; charset=utf-8",
      "curl": null
    }
  ]
}