{
  "resource": "User",
  "resource_explanation": null,
  "http_method": "GET",
  "route": "/users/:id",
  "description": "show:success",
  "explanation": null,
  "parameters": [

  ],
  "response_fields": [

  ],
  "requests": [
    {
      "request_method": "GET",
      "request_path": "/users/26",
      "request_body": null,
      "request_headers": {
        "Content-Type": "application/json",
        "Accept": "application/json",
        "Authorization": "eyJ0eXAiOiJKV1QiLCJhbGciOiJIUzI1NiJ9.eyJleHAiOjE1NDY2MDU0MDcsInN1YiI6MjZ9.8Jttbbn94z0mDa70eFiq5H_dTE8H-61_u24e7Vda6sQ"
      },
      "request_query_parameters": {
        "{}": null
      },
      "request_content_type": "application/json",
      "response_status": 200,
      "response_status_text": "OK",
      "response_body": "{\n  \"data\": {\n    \"id\": \"26\",\n    \"type\": \"user\",\n    \"attributes\": {\n      \"agree_tos\": false,\n      \"first_name\": \"Faralda\",\n      \"last_name\": \"Fleet\",\n      \"avatar\": \"https://robohash.org/faralda-the-fleet.png?size=300x300&set=set1\",\n      \"street_number\": null,\n      \"route\": null,\n      \"locality\": \"West Anibal\",\n      \"admin_area_level_1\": \"IA\",\n      \"admin_area_level_2\": null,\n      \"country\": \"United States\",\n      \"postal_code\": null,\n      \"latitude\": \"40.73061\",\n      \"longitude\": \"-73.935242\",\n      \"phone_country_code\": \"1\",\n      \"phone_area_code\": null,\n      \"phone_number\": \"1-772-984-9573 x4206\",\n      \"available_mornings\": null,\n      \"available_afternoons\": null,\n      \"available_evenings\": null,\n      \"available_weekends\": null,\n      \"network_code\": \"demo\",\n      \"facebook_id\": \"1331599\",\n      \"activities\": [\n\n      ],\n      \"phone\": \"() 1-7-72-984-9573 x4206\",\n      \"full_address\": \" , West Anibal, IA, United States \",\n      \"profile_blurb\": null,\n      \"onboarding_care_type\": null,\n      \"date_created\": \"2019-01-03T12:36:47.946Z\"\n    },\n    \"relationships\": {\n      \"children\": {\n        \"data\": [\n          {\n            \"id\": \"17\",\n            \"type\": \"child\"\n          },\n          {\n            \"id\": \"18\",\n            \"type\": \"child\"\n          }\n        ]\n      }\n    }\n  },\n  \"included\": [\n    {\n      \"id\": \"17\",\n      \"type\": \"child\",\n      \"attributes\": {\n        \"parent_id\": 26,\n        \"age\": 2\n      },\n      \"relationships\": {\n        \"parent\": {\n          \"data\": {\n            \"id\": \"26\",\n            \"type\": \"user\"\n          }\n        }\n      }\n    },\n    {\n      \"id\": \"18\",\n      \"type\": \"child\",\n      \"attributes\": {\n        \"parent_id\": 26,\n        \"age\": 4\n      },\n      \"relationships\": {\n        \"parent\": {\n          \"data\": {\n            \"id\": \"26\",\n            \"type\": \"user\"\n          }\n        }\n      }\n    }\n  ],\n  \"jwt\": \"eyJ0eXAiOiJKV1QiLCJhbGciOiJIUzI1NiJ9.eyJleHAiOjE1NDY2MDU0MDcsInN1YiI6MjYsImVtYWlsIjoiYWRhbV9ib3JlckBleGFtcGxlLm5ldCIsIm5ldHdvcmtfY29kZSI6ImRlbW8ifQ.4xEInmKjVruGGR0iXeQF1sC5xYqQdfmpe4Ab1tk5KrQ\"\n}",
      "response_headers": {
        "Content-Type": "application/vnd.api+json; charset=utf-8"
      },
      "response_content_type": "application/vnd.api+json; charset=utf-8",
      "curl": null
    }
  ]
}