{
  "resource": "EventSeries",
  "resource_explanation": null,
  "http_method": "GET",
  "route": "/api/event_series",
  "description": "index:success",
  "explanation": null,
  "parameters": [

  ],
  "response_fields": [

  ],
  "requests": [
    {
      "request_method": "GET",
      "request_path": "/api/event_series",
      "request_body": null,
      "request_headers": {
        "Content-Type": "application/json",
        "Accept": "application/json",
        "Authorization": "eyJ0eXAiOiJKV1QiLCJhbGciOiJIUzI1NiJ9.eyJleHAiOjE1NDUzOTIxOTgsInN1YiI6M30.--sJ9eB7pzCYzfp03qrZPXixDXioLk7epNxZZ3Tnmqk"
      },
      "request_query_parameters": {
        "{}": null
      },
      "request_content_type": "application/json",
      "response_status": 200,
      "response_status_text": "OK",
      "response_body": "{\n  \"data\": [\n    {\n      \"id\": \"2\",\n      \"type\": \"event_series\",\n      \"attributes\": {\n        \"name\": \"Al K. Seltzer\",\n        \"start_date\": \"2019-01-05\",\n        \"has_pet\": true,\n        \"activity_names\": [\n          \"Oliver Sutton\"\n        ],\n        \"foods\": [\n          \"Bruschette with Tomato\"\n        ],\n        \"house_rules\": \"Ratione illo iusto. Atque quidem ut. Quia quas ullam.\",\n        \"pet_description\": \"Voluptatum occaecati quasi. Est qui quo. Consequatur sed optio.\",\n        \"starts_at\": \"11:12\",\n        \"ends_at\": \"14:12\"\n      },\n      \"relationships\": {\n        \"event_hosts\": {\n          \"data\": [\n            {\n              \"id\": \"3\",\n              \"type\": \"event_host\"\n            },\n            {\n              \"id\": \"4\",\n              \"type\": \"event_host\"\n            }\n          ]\n        }\n      }\n    }\n  ],\n  \"included\": [\n    {\n      \"id\": \"3\",\n      \"type\": \"event_host\",\n      \"attributes\": {\n        \"name\": \"Donetta Gleason\",\n        \"email\": \"carleen@yahoo.com\",\n        \"phone\": \"1-361-191-4958\"\n      }\n    },\n    {\n      \"id\": \"4\",\n      \"type\": \"event_host\",\n      \"attributes\": {\n        \"name\": \"Rodger Collier V\",\n        \"email\": \"wayne@gmail.com\",\n        \"phone\": \"204.757.4997\"\n      }\n    }\n  ]\n}",
      "response_headers": {
        "Content-Type": "application/vnd.api+json; charset=utf-8"
      },
      "response_content_type": "application/vnd.api+json; charset=utf-8",
      "curl": null
    }
  ]
}